{"assert/entro8/Frame 17.png":["assert/entro8/Frame 17.png"],"assert/entro8/Group 315.png":["assert/entro8/Group 315.png"],"assert/entro8/Group 317.png":["assert/entro8/Group 317.png"],"assert/entro8/Group 318.png":["assert/entro8/Group 318.png"],"assert/entro8/Group 319.png":["assert/entro8/Group 319.png"],"assert/entro8/Group 320.png":["assert/entro8/Group 320.png"],"assert/entro8/Group 321.png":["assert/entro8/Group 321.png"],"assert/entro8/logo/512x512.png":["assert/entro8/logo/512x512.png"],"assert/figma/1.png":["assert/figma/1.png"],"assert/figma/2.png":["assert/figma/2.png"],"assert/figma/3.png":["assert/figma/3.png"],"assert/figma/4.png":["assert/figma/4.png"],"assert/figma/5.png":["assert/figma/5.png"],"assert/figma/6.png":["assert/figma/6.png"],"assert/figma/7.png":["assert/figma/7.png"],"assert/figma/8.png":["assert/figma/8.png"],"assert/flutter/1.png":["assert/flutter/1.png"],"assert/flutter/10.png":["assert/flutter/10.png"],"assert/flutter/11.png":["assert/flutter/11.png"],"assert/flutter/12.png":["assert/flutter/12.png"],"assert/flutter/13.png":["assert/flutter/13.png"],"assert/flutter/14.png":["assert/flutter/14.png"],"assert/flutter/15.png":["assert/flutter/15.png"],"assert/flutter/16.png":["assert/flutter/16.png"],"assert/flutter/17.png":["assert/flutter/17.png"],"assert/flutter/2.png":["assert/flutter/2.png"],"assert/flutter/3.png":["assert/flutter/3.png"],"assert/flutter/4.png":["assert/flutter/4.png"],"assert/flutter/5.png":["assert/flutter/5.png"],"assert/flutter/6.png":["assert/flutter/6.png"],"assert/flutter/7.png":["assert/flutter/7.png"],"assert/flutter/8.png":["assert/flutter/8.png"],"assert/flutter/9.png":["assert/flutter/9.png"],"assert/font/PTSerif-Regular.ttf":["assert/font/PTSerif-Regular.ttf"],"assert/font/Pacifico-Regular.ttf":["assert/font/Pacifico-Regular.ttf"],"assert/life/1.jpg":["assert/life/1.jpg"],"assert/life/3.png":["assert/life/3.png"],"assert/life/4.png":["assert/life/4.png"],"assert/top_images/IMG_0052.JPG":["assert/top_images/IMG_0052.JPG"],"assert/top_images/IMG_0056.jpg":["assert/top_images/IMG_0056.jpg"],"assert/top_images/IMG_0057.jpg":["assert/top_images/IMG_0057.jpg"],"assert/top_images/IMG_0076.JPG":["assert/top_images/IMG_0076.JPG"],"packages/cupertino_icons/assets/CupertinoIcons.ttf":["packages/cupertino_icons/assets/CupertinoIcons.ttf"],"packages/font_awesome_flutter/lib/fonts/fa-brands-400.ttf":["packages/font_awesome_flutter/lib/fonts/fa-brands-400.ttf"],"packages/font_awesome_flutter/lib/fonts/fa-regular-400.ttf":["packages/font_awesome_flutter/lib/fonts/fa-regular-400.ttf"],"packages/font_awesome_flutter/lib/fonts/fa-solid-900.ttf":["packages/font_awesome_flutter/lib/fonts/fa-solid-900.ttf"]}